setup.py
distributions_probability_jay/Binomialdistribution.py
distributions_probability_jay/Gaussiandistribution.py
distributions_probability_jay/Generaldistribution.py
distributions_probability_jay/__init__.py
distributions_probability_jay.egg-info/PKG-INFO
distributions_probability_jay.egg-info/SOURCES.txt
distributions_probability_jay.egg-info/dependency_links.txt
distributions_probability_jay.egg-info/not-zip-safe
distributions_probability_jay.egg-info/top_level.txt