Metadata-Version: 1.0
Name: distributions-probability-jay
Version: 0.1
Summary: Gaussian and Binomial distributions
Home-page: UNKNOWN
Author: Jay Shankar Gupta
Author-email: UNKNOWN
License: UNKNOWN
Platform: UNKNOWN
